README.md
setup.py
avilabs_snippets.egg-info/PKG-INFO
avilabs_snippets.egg-info/SOURCES.txt
avilabs_snippets.egg-info/dependency_links.txt
avilabs_snippets.egg-info/requires.txt
avilabs_snippets.egg-info/top_level.txt
snippets/__init__.py
snippets/color_printer.py
snippets/log_config.py
snippets/plotters.py
snippets/retry_wrapper.py