Metadata-Version: 1.0
Name: avilabs-snippets
Version: 0.0.3
Summary: Grab bag of useful snippets
Home-page: https://gitlab.com/avilay/snippets
Author: Avilay Parekh
Author-email: avilay@gmail.com
License: MIT
Platform: UNKNOWN
